LICENSE.md
MANIFEST.in
README.md
setup.py
pydie/__init__.py
pydie/anu.py
pydie/api.py
pydie/cli.py
pydie/enums.py
pydie/parser.py
pydie/rollmethods.py
pydie.egg-info/PKG-INFO
pydie.egg-info/SOURCES.txt
pydie.egg-info/dependency_links.txt
pydie.egg-info/entry_points.txt
pydie.egg-info/requires.txt
pydie.egg-info/top_level.txt