Metadata-Version: 1.1
Name: pydie
Version: 0.2.5
Summary: Generate a random roll from a n-number of an n-sided die.
Home-page: http://github.com/aubricus/pydie
Author: Aubrey Taylor
Author-email: aubricus@gmail.com
License: License
